{"k":"0000000078","o":"0000000102","v":"001"}
{"_id":2,"_uid":2,"_dt":1574306787506,"_s":"a5dc9be8d8c21f907f7f50162858322d"}
{"Time":"1000","fob_ID":"1","hub_ID":"0","Name":"30.99","Checked-In":"0","_id":{"$wrap":"$oid","v":2}}
{"k":"0000000078","o":"0000000102","v":"001"}
{"_id":3,"_uid":3,"_dt":1574306787687,"_s":"44dcfb1027c93a9c4b7a53b88fb2a1eb"}
{"Time":"1000","fob_ID":"2","hub_ID":"0","Name":"32.61","Checked-In":"0","_id":{"$wrap":"$oid","v":3}}
{"k":"0000000078","o":"0000000102","v":"001"}
{"_id":4,"_uid":4,"_dt":1574306787704,"_s":"48c8d7f42a0ad0376032e1a411dcaaf1"}
{"Time":"1000","fob_ID":"3","hub_ID":"0","Name":"34.24","Checked-In":"0","_id":{"$wrap":"$oid","v":4}}
{"k":"0000000078","o":"0000000102","v":"001"}
{"_id":5,"_uid":5,"_dt":1574306787711,"_s":"80816810dba56f44a4719bf093457b1c"}
{"Time":"1000","fob_ID":"4","hub_ID":"0","Name":"33.93","Checked-In":"0","_id":{"$wrap":"$oid","v":5}}
{"k":"0000000078","o":"0000000102","v":"001"}
{"_id":6,"_uid":6,"_dt":1574306787717,"_s":"e81558c38ab550a022a8f6aba965fa63"}
{"Time":"1000","fob_ID":"5","hub_ID":"0","Name":"32.16","Checked-In":"1","_id":{"$wrap":"$oid","v":6}}
{"k":"0000000078","o":"0000000102","v":"001"}
{"_id":7,"_uid":7,"_dt":1574306787723,"_s":"88a8d3956c95ec05b3436515f223df96"}
{"Time":"2000","fob_ID":"1","hub_ID":"1","Name":"39.84","Checked-In":"1","_id":{"$wrap":"$oid","v":7}}
{"k":"0000000078","o":"0000000102","v":"001"}
{"_id":8,"_uid":8,"_dt":1574306787729,"_s":"d4842187160262a57733954550e5d0b9"}
{"Time":"2000","fob_ID":"2","hub_ID":"1","Name":"39.15","Checked-In":"1","_id":{"$wrap":"$oid","v":8}}
{"k":"0000000078","o":"0000000102","v":"001"}
{"_id":9,"_uid":9,"_dt":1574306787736,"_s":"57e820b5162afa4b5997c6c0fa95ad03"}
{"Time":"2000","fob_ID":"3","hub_ID":"1","Name":"35.31","Checked-In":"1","_id":{"$wrap":"$oid","v":9}}
{"k":"0000000080","o":"0000000103","v":"001"}
{"_id":10,"_uid":10,"_dt":1574306787741,"_s":"9cc33bf6fa3c45c7e381d12d7a8ee2a3"}
{"Time":"2000","fob_ID":"4","hub_ID":"0","Name":"32.11","Checked-In":"1","_id":{"$wrap":"$oid","v":10}}
{"k":"0000000080","o":"0000000103","v":"001"}
{"_id":11,"_uid":11,"_dt":1574306787747,"_s":"0bfee1255f2fb115099257c91a16465f"}
{"Time":"2000","fob_ID":"5","hub_ID":"1","Name":"37.64","Checked-In":"1","_id":{"$wrap":"$oid","v":11}}
{"k":"0000000080","o":"0000000103","v":"001"}
{"_id":12,"_uid":12,"_dt":1574306787753,"_s":"b95110345ef73f7d0f67fa99eadb2bed"}
{"Time":"3000","fob_ID":"1","hub_ID":"0","Name":"31.79","Checked-In":"1","_id":{"$wrap":"$oid","v":12}}
{"k":"0000000080","o":"0000000103","v":"001"}
{"_id":13,"_uid":13,"_dt":1574306787759,"_s":"25bc994dcb0039149650c30f86f96e9e"}
{"Time":"3000","fob_ID":"2","hub_ID":"0","Name":"34.59","Checked-In":"1","_id":{"$wrap":"$oid","v":13}}
{"k":"0000000080","o":"0000000103","v":"001"}
{"_id":14,"_uid":14,"_dt":1574306787765,"_s":"2c89603771a551647b4f30d74a1dc9bb"}
{"Time":"3000","fob_ID":"3","hub_ID":"1","Name":"39.74","Checked-In":"1","_id":{"$wrap":"$oid","v":14}}
{"k":"0000000080","o":"0000000103","v":"001"}
{"_id":15,"_uid":15,"_dt":1574306787771,"_s":"a486bcad5f65a51d4d75757b9f600ded"}
{"Time":"3000","fob_ID":"4","hub_ID":"0","Name":"32.78","Checked-In":"1","_id":{"$wrap":"$oid","v":15}}
{"k":"0000000080","o":"0000000103","v":"001"}
{"_id":16,"_uid":16,"_dt":1574306787777,"_s":"8117d30f344d257bd470a687259792eb"}
{"Time":"3000","fob_ID":"5","hub_ID":"0","Name":"32.19","Checked-In":"1","_id":{"$wrap":"$oid","v":16}}
{"k":"0000000080","o":"0000000103","v":"001"}
{"_id":17,"_uid":17,"_dt":1574306787783,"_s":"c6a561f9b3d85f19b6bcd7d0089af957"}
{"Time":"4000","fob_ID":"1","hub_ID":"1","Name":"38.92","Checked-In":"1","_id":{"$wrap":"$oid","v":17}}
{"k":"0000000080","o":"0000000103","v":"001"}
{"_id":18,"_uid":18,"_dt":1574306787789,"_s":"ddfa45c9f915ee7397df7e7af82c1d4e"}
{"Time":"4000","fob_ID":"2","hub_ID":"1","Name":"38.37","Checked-In":"1","_id":{"$wrap":"$oid","v":18}}
{"k":"0000000080","o":"0000000103","v":"001"}
{"_id":19,"_uid":19,"_dt":1574306787795,"_s":"61a650c92646cc61889e62df610b968c"}
{"Time":"4000","fob_ID":"3","hub_ID":"1","Name":"36.13","Checked-In":"1","_id":{"$wrap":"$oid","v":19}}
{"k":"0000000080","o":"0000000103","v":"001"}
{"_id":20,"_uid":20,"_dt":1574306787801,"_s":"551ae4052bdcab7b6ab76d87355a94bf"}
{"Time":"4000","fob_ID":"4","hub_ID":"0","Name":"30.65","Checked-In":"0","_id":{"$wrap":"$oid","v":20}}
{"k":"0000000080","o":"0000000103","v":"001"}
{"_id":21,"_uid":21,"_dt":1574306787808,"_s":"491183e7161294a5c6d97118a416ea7e"}
{"Time":"4000","fob_ID":"5","hub_ID":"1","Name":"36.15","Checked-In":"0","_id":{"$wrap":"$oid","v":21}}
{"k":"0000000080","o":"0000000103","v":"001"}
{"_id":22,"_uid":22,"_dt":1574306787814,"_s":"0aea702179da8c80d09fd151bb3fadad"}
{"Time":"5000","fob_ID":"1","hub_ID":"0","Name":"33.23","Checked-In":"1","_id":{"$wrap":"$oid","v":22}}
{"k":"0000000080","o":"0000000103","v":"001"}
{"_id":23,"_uid":23,"_dt":1574306787821,"_s":"d85d6e033c23932f04edfa2e2a06f839"}
{"Time":"5000","fob_ID":"2","hub_ID":"1","Name":"38.79","Checked-In":"0","_id":{"$wrap":"$oid","v":23}}
{"k":"0000000080","o":"0000000103","v":"001"}
{"_id":24,"_uid":24,"_dt":1574306787826,"_s":"e3d34ef61b7fbfe3f5c0f75b3e4c59d2"}
{"Time":"5000","fob_ID":"3","hub_ID":"0","Name":"32.52","Checked-In":"0","_id":{"$wrap":"$oid","v":24}}
{"k":"0000000080","o":"0000000103","v":"001"}
{"_id":25,"_uid":25,"_dt":1574306787833,"_s":"0415e878a44a21126667d22028592a0e"}
{"Time":"5000","fob_ID":"4","hub_ID":"0","Name":"32.51","Checked-In":"0","_id":{"$wrap":"$oid","v":25}}
{"k":"0000000080","o":"0000000103","v":"001"}
{"_id":26,"_uid":26,"_dt":1574306787839,"_s":"6d458cf8ccac15c97e67b87a1a60d926"}
{"Time":"5000","fob_ID":"5","hub_ID":"1","Name":"36.72","Checked-In":"0","_id":{"$wrap":"$oid","v":26}}
{"k":"0000000080","o":"0000000103","v":"001"}
{"_id":27,"_uid":27,"_dt":1574306787845,"_s":"e8bcb40153a28e89a01651559b87b1d6"}
{"Time":"6000","fob_ID":"1","hub_ID":"0","Name":"32.05","Checked-In":"0","_id":{"$wrap":"$oid","v":27}}
{"k":"0000000080","o":"0000000103","v":"001"}
{"_id":28,"_uid":28,"_dt":1574306787851,"_s":"6daa609d0c4322d997c8706a5fece0ec"}
{"Time":"6000","fob_ID":"2","hub_ID":"0","Name":"30.20","Checked-In":"0","_id":{"$wrap":"$oid","v":28}}
{"k":"0000000080","o":"0000000103","v":"001"}
{"_id":29,"_uid":29,"_dt":1574306787857,"_s":"c9f0f0bce4cbc4c9b200d64ab48a4ac2"}
{"Time":"6000","fob_ID":"3","hub_ID":"0","Name":"30.72","Checked-In":"1","_id":{"$wrap":"$oid","v":29}}
{"k":"0000000080","o":"0000000103","v":"001"}
{"_id":30,"_uid":30,"_dt":1574306787863,"_s":"f11095d7a5bf88e07951bf38664da117"}
{"Time":"6000","fob_ID":"4","hub_ID":"0","Name":"32.74","Checked-In":"1","_id":{"$wrap":"$oid","v":30}}
{"k":"0000000080","o":"0000000103","v":"001"}
{"_id":31,"_uid":31,"_dt":1574306787870,"_s":"a759281c3787c64960d41e8dd2503e95"}
{"Time":"6000","fob_ID":"5","hub_ID":"1","Name":"37.99","Checked-In":"1","_id":{"$wrap":"$oid","v":31}}
{"k":"0000000080","o":"0000000103","v":"001"}
{"_id":32,"_uid":32,"_dt":1574306787876,"_s":"6e2e285b57285683eb24ed87b689a8fe"}
{"Time":"7000","fob_ID":"1","hub_ID":"0","Name":"32.43","Checked-In":"1","_id":{"$wrap":"$oid","v":32}}
{"k":"0000000080","o":"0000000103","v":"001"}
{"_id":33,"_uid":33,"_dt":1574306787882,"_s":"2eb7ddc0131af83de62060599e9c2a95"}
{"Time":"7000","fob_ID":"2","hub_ID":"0","Name":"30.80","Checked-In":"1","_id":{"$wrap":"$oid","v":33}}
{"k":"0000000080","o":"0000000103","v":"001"}
{"_id":34,"_uid":34,"_dt":1574306787889,"_s":"5f5e71fc07c8ef8dbeddb5041a9a0ebb"}
{"Time":"7000","fob_ID":"3","hub_ID":"0","Name":"35.55","Checked-In":"1","_id":{"$wrap":"$oid","v":34}}
{"k":"0000000080","o":"0000000103","v":"001"}
{"_id":35,"_uid":35,"_dt":1574306787895,"_s":"156c479aa90badb01f625016231f6d0c"}
{"Time":"7000","fob_ID":"4","hub_ID":"0","Name":"32.59","Checked-In":"1","_id":{"$wrap":"$oid","v":35}}
{"k":"0000000080","o":"0000000103","v":"001"}
{"_id":36,"_uid":36,"_dt":1574306787901,"_s":"7a53526eecdc76fd7729da2d2d6f40f6"}
{"Time":"7000","fob_ID":"5","hub_ID":"0","Name":"33.09","Checked-In":"0","_id":{"$wrap":"$oid","v":36}}
{"k":"0000000080","o":"0000000103","v":"001"}
{"_id":37,"_uid":37,"_dt":1574306787908,"_s":"ede0988b230ed95faf94ed539bf34410"}
{"Time":"8000","fob_ID":"1","hub_ID":"0","Name":"32.53","Checked-In":"1","_id":{"$wrap":"$oid","v":37}}
{"k":"0000000080","o":"0000000103","v":"001"}
{"_id":38,"_uid":38,"_dt":1574306787915,"_s":"fafc515f88cf98dff0462e6bddb5cfe4"}
{"Time":"8000","fob_ID":"2","hub_ID":"1","Name":"35.42","Checked-In":"0","_id":{"$wrap":"$oid","v":38}}
{"k":"0000000080","o":"0000000103","v":"001"}
{"_id":39,"_uid":39,"_dt":1574306787921,"_s":"5b5d07b28789d0b4d0cfff5995cfe7df"}
{"Time":"8000","fob_ID":"3","hub_ID":"0","Name":"33.32","Checked-In":"1","_id":{"$wrap":"$oid","v":39}}
{"k":"0000000080","o":"0000000103","v":"001"}
{"_id":40,"_uid":40,"_dt":1574306787927,"_s":"aed44b815e16fcd5d4408248de4acff2"}
{"Time":"8000","fob_ID":"4","hub_ID":"1","Name":"39.43","Checked-In":"0","_id":{"$wrap":"$oid","v":40}}
{"k":"0000000080","o":"0000000103","v":"001"}
{"_id":41,"_uid":41,"_dt":1574306787934,"_s":"ad7d5b7489886dd96f12c147210e1324"}
{"Time":"8000","fob_ID":"5","hub_ID":"0","Name":"30.02","Checked-In":"1","_id":{"$wrap":"$oid","v":41}}
{"k":"0000000080","o":"0000000041","v":"001"}
{"_id":42,"_uid":42,"_dt":1574306787940,"_s":"22a9d437beda24a9a18658c899d6741b"}
{"Time":"","_id":{"$wrap":"$oid","v":42}}
{"k":"0000000080","o":"0000000103","v":"001"}
{"_id":43,"_uid":43,"_dt":1574306938205,"_s":"4fb5d252cacb8afc64ea7a63a9a7754b"}
{"Time":"1000","fob_ID":"1","hub_ID":"0","Name":"30.99","Checked-In":"0","_id":{"$wrap":"$oid","v":43}}
{"k":"0000000080","o":"0000000103","v":"001"}
{"_id":44,"_uid":44,"_dt":1574306938289,"_s":"ea7bc0ced7aad57ae4c0c34545765bac"}
{"Time":"1000","fob_ID":"2","hub_ID":"0","Name":"32.61","Checked-In":"0","_id":{"$wrap":"$oid","v":44}}
{"k":"0000000080","o":"0000000103","v":"001"}
{"_id":45,"_uid":45,"_dt":1574306938322,"_s":"b0f034ea69621f378173eabef3a577b0"}
{"Time":"1000","fob_ID":"3","hub_ID":"0","Name":"34.24","Checked-In":"0","_id":{"$wrap":"$oid","v":45}}
{"k":"0000000080","o":"0000000103","v":"001"}
{"_id":46,"_uid":46,"_dt":1574306938346,"_s":"98d31b616184650ea2ca6b1a747ac85c"}
{"Time":"1000","fob_ID":"4","hub_ID":"0","Name":"33.93","Checked-In":"0","_id":{"$wrap":"$oid","v":46}}
{"k":"0000000080","o":"0000000103","v":"001"}
{"_id":47,"_uid":47,"_dt":1574306938354,"_s":"e88d627caa9d854cc0fd4d452baf6ca9"}
{"Time":"1000","fob_ID":"5","hub_ID":"0","Name":"32.16","Checked-In":"1","_id":{"$wrap":"$oid","v":47}}
{"k":"0000000080","o":"0000000103","v":"001"}
{"_id":48,"_uid":48,"_dt":1574306938360,"_s":"ad199c47b9be11d4acffdcdb583ae8f7"}
{"Time":"2000","fob_ID":"1","hub_ID":"1","Name":"39.84","Checked-In":"1","_id":{"$wrap":"$oid","v":48}}
{"k":"0000000080","o":"0000000103","v":"001"}
{"_id":49,"_uid":49,"_dt":1574306938381,"_s":"603a624cb4474582f73188c6812c7a18"}
{"Time":"2000","fob_ID":"2","hub_ID":"1","Name":"39.15","Checked-In":"1","_id":{"$wrap":"$oid","v":49}}
{"k":"0000000080","o":"0000000103","v":"001"}
{"_id":50,"_uid":50,"_dt":1574306938393,"_s":"0ac032f054f3dfa44b4b08fb7e4b75c2"}
{"Time":"2000","fob_ID":"3","hub_ID":"1","Name":"35.31","Checked-In":"1","_id":{"$wrap":"$oid","v":50}}
{"k":"0000000080","o":"0000000103","v":"001"}
{"_id":51,"_uid":51,"_dt":1574306938409,"_s":"657bb6b14bc7e1b31eb583aec839a847"}
{"Time":"2000","fob_ID":"4","hub_ID":"0","Name":"32.11","Checked-In":"1","_id":{"$wrap":"$oid","v":51}}
{"k":"0000000080","o":"0000000103","v":"001"}
{"_id":52,"_uid":52,"_dt":1574306938429,"_s":"f2ba667f18f63eff53e88a3b6c935fd7"}
{"Time":"2000","fob_ID":"5","hub_ID":"1","Name":"37.64","Checked-In":"1","_id":{"$wrap":"$oid","v":52}}
{"k":"0000000080","o":"0000000103","v":"001"}
{"_id":53,"_uid":53,"_dt":1574306938436,"_s":"80569f204616e9283696f81686df3cd2"}
{"Time":"3000","fob_ID":"1","hub_ID":"0","Name":"31.79","Checked-In":"1","_id":{"$wrap":"$oid","v":53}}
{"k":"0000000080","o":"0000000103","v":"001"}
{"_id":54,"_uid":54,"_dt":1574306938442,"_s":"3abd3ae4feec344f726fa905dfbbedde"}
{"Time":"3000","fob_ID":"2","hub_ID":"0","Name":"34.59","Checked-In":"1","_id":{"$wrap":"$oid","v":54}}
{"k":"0000000080","o":"0000000103","v":"001"}
{"_id":55,"_uid":55,"_dt":1574306938448,"_s":"4122ceacf395e194feb9fa84ecf7caee"}
{"Time":"3000","fob_ID":"3","hub_ID":"1","Name":"39.74","Checked-In":"1","_id":{"$wrap":"$oid","v":55}}
{"k":"0000000080","o":"0000000103","v":"001"}
{"_id":56,"_uid":56,"_dt":1574306938455,"_s":"4edcf11146f679a2b2d7952bde4405e1"}
{"Time":"3000","fob_ID":"4","hub_ID":"0","Name":"32.78","Checked-In":"1","_id":{"$wrap":"$oid","v":56}}
{"k":"0000000080","o":"0000000103","v":"001"}
{"_id":57,"_uid":57,"_dt":1574306938462,"_s":"c47cacd657daf3e9e6a352041a0da89e"}
{"Time":"3000","fob_ID":"5","hub_ID":"0","Name":"32.19","Checked-In":"1","_id":{"$wrap":"$oid","v":57}}
{"k":"0000000080","o":"0000000103","v":"001"}
{"_id":58,"_uid":58,"_dt":1574306938469,"_s":"ea44aeee8d6f5a9b7ee02ab428ce3555"}
{"Time":"4000","fob_ID":"1","hub_ID":"1","Name":"38.92","Checked-In":"1","_id":{"$wrap":"$oid","v":58}}
{"k":"0000000080","o":"0000000103","v":"001"}
{"_id":59,"_uid":59,"_dt":1574306938475,"_s":"f269179f62dea049111d300626589fa5"}
{"Time":"4000","fob_ID":"2","hub_ID":"1","Name":"38.37","Checked-In":"1","_id":{"$wrap":"$oid","v":59}}
{"k":"0000000080","o":"0000000103","v":"001"}
{"_id":60,"_uid":60,"_dt":1574306938482,"_s":"fb6f10ff70c5c02fd5712e927b0883ee"}
{"Time":"4000","fob_ID":"3","hub_ID":"1","Name":"36.13","Checked-In":"1","_id":{"$wrap":"$oid","v":60}}
{"k":"0000000080","o":"0000000103","v":"001"}
{"_id":61,"_uid":61,"_dt":1574306938488,"_s":"1885b870161c2e875b8a03bf1fb74799"}
{"Time":"4000","fob_ID":"4","hub_ID":"0","Name":"30.65","Checked-In":"0","_id":{"$wrap":"$oid","v":61}}
{"k":"0000000080","o":"0000000103","v":"001"}
{"_id":62,"_uid":62,"_dt":1574306938495,"_s":"95f3bcf136b8e37e358f2c2e14ef8d16"}
{"Time":"4000","fob_ID":"5","hub_ID":"1","Name":"36.15","Checked-In":"0","_id":{"$wrap":"$oid","v":62}}
{"k":"0000000080","o":"0000000103","v":"001"}
{"_id":63,"_uid":63,"_dt":1574306938502,"_s":"af2e1f97b261fe9af40f96466942fa01"}
{"Time":"5000","fob_ID":"1","hub_ID":"0","Name":"33.23","Checked-In":"1","_id":{"$wrap":"$oid","v":63}}
{"k":"0000000080","o":"0000000103","v":"001"}
{"_id":64,"_uid":64,"_dt":1574306938508,"_s":"bc7d3e2fe6ddbb34163e3d148444eb54"}
{"Time":"5000","fob_ID":"2","hub_ID":"1","Name":"38.79","Checked-In":"0","_id":{"$wrap":"$oid","v":64}}
{"k":"0000000080","o":"0000000103","v":"001"}
{"_id":65,"_uid":65,"_dt":1574306938515,"_s":"0d3aa9785a496c49b69e8714145ce689"}
{"Time":"5000","fob_ID":"3","hub_ID":"0","Name":"32.52","Checked-In":"0","_id":{"$wrap":"$oid","v":65}}
{"k":"0000000080","o":"0000000103","v":"001"}
{"_id":66,"_uid":66,"_dt":1574306938521,"_s":"e4ac41e9c3213b9c3144317336e2bee6"}
{"Time":"5000","fob_ID":"4","hub_ID":"0","Name":"32.51","Checked-In":"0","_id":{"$wrap":"$oid","v":66}}
{"k":"0000000080","o":"0000000103","v":"001"}
{"_id":67,"_uid":67,"_dt":1574306938533,"_s":"b12c3fcdcd295b54a3fc5ebc41fb2400"}
{"Time":"5000","fob_ID":"5","hub_ID":"1","Name":"36.72","Checked-In":"0","_id":{"$wrap":"$oid","v":67}}
{"k":"0000000080","o":"0000000103","v":"001"}
{"_id":68,"_uid":68,"_dt":1574306938539,"_s":"3bc86673e8d94efc8f190b0a8d980d37"}
{"Time":"6000","fob_ID":"1","hub_ID":"0","Name":"32.05","Checked-In":"0","_id":{"$wrap":"$oid","v":68}}
{"k":"0000000080","o":"0000000103","v":"001"}
{"_id":69,"_uid":69,"_dt":1574306938546,"_s":"edab0fa99bcd757215ff3c626e869722"}
{"Time":"6000","fob_ID":"2","hub_ID":"0","Name":"30.20","Checked-In":"0","_id":{"$wrap":"$oid","v":69}}
{"k":"0000000080","o":"0000000103","v":"001"}
{"_id":70,"_uid":70,"_dt":1574306938567,"_s":"1cca59f8b36c3e220954f34e9f1cbbab"}
{"Time":"6000","fob_ID":"3","hub_ID":"0","Name":"30.72","Checked-In":"1","_id":{"$wrap":"$oid","v":70}}
{"k":"0000000080","o":"0000000103","v":"001"}
{"_id":71,"_uid":71,"_dt":1574306938573,"_s":"049790dede502df7c99cced74d50a12a"}
{"Time":"6000","fob_ID":"4","hub_ID":"0","Name":"32.74","Checked-In":"1","_id":{"$wrap":"$oid","v":71}}
{"k":"0000000080","o":"0000000103","v":"001"}
{"_id":72,"_uid":72,"_dt":1574306938580,"_s":"c218ae07cb90d76dc844e76939b19f3f"}
{"Time":"6000","fob_ID":"5","hub_ID":"1","Name":"37.99","Checked-In":"1","_id":{"$wrap":"$oid","v":72}}
{"k":"0000000080","o":"0000000103","v":"001"}
{"_id":73,"_uid":73,"_dt":1574306938587,"_s":"bf2a5016e36db818a37c9c12a9b10dc0"}
{"Time":"7000","fob_ID":"1","hub_ID":"0","Name":"32.43","Checked-In":"1","_id":{"$wrap":"$oid","v":73}}
{"k":"0000000080","o":"0000000103","v":"001"}
{"_id":74,"_uid":74,"_dt":1574306938593,"_s":"d130120d96a7a60ee7a4e459a0a4b67d"}
{"Time":"7000","fob_ID":"2","hub_ID":"0","Name":"30.80","Checked-In":"1","_id":{"$wrap":"$oid","v":74}}
{"k":"0000000080","o":"0000000103","v":"001"}
{"_id":75,"_uid":75,"_dt":1574306938600,"_s":"ab22e624afbb555441bed9be2f33fff7"}
{"Time":"7000","fob_ID":"3","hub_ID":"0","Name":"35.55","Checked-In":"1","_id":{"$wrap":"$oid","v":75}}
{"k":"0000000080","o":"0000000103","v":"001"}
{"_id":76,"_uid":76,"_dt":1574306938606,"_s":"30b63a6afc81e6f2dac50de1b62c1006"}
{"Time":"7000","fob_ID":"4","hub_ID":"0","Name":"32.59","Checked-In":"1","_id":{"$wrap":"$oid","v":76}}
{"k":"0000000080","o":"0000000103","v":"001"}
{"_id":77,"_uid":77,"_dt":1574306938613,"_s":"e1edc745af4386528c1b7869b5fb1757"}
{"Time":"7000","fob_ID":"5","hub_ID":"0","Name":"33.09","Checked-In":"0","_id":{"$wrap":"$oid","v":77}}
{"k":"0000000080","o":"0000000103","v":"001"}
{"_id":78,"_uid":78,"_dt":1574306938620,"_s":"4e925eb2bf7fb36e79696ebe468a8662"}
{"Time":"8000","fob_ID":"1","hub_ID":"0","Name":"32.53","Checked-In":"1","_id":{"$wrap":"$oid","v":78}}
{"k":"0000000080","o":"0000000103","v":"001"}
{"_id":79,"_uid":79,"_dt":1574306938627,"_s":"b0ae8522b9c228cb5ea1435648718842"}
{"Time":"8000","fob_ID":"2","hub_ID":"1","Name":"35.42","Checked-In":"0","_id":{"$wrap":"$oid","v":79}}
{"k":"0000000080","o":"0000000103","v":"001"}
{"_id":80,"_uid":80,"_dt":1574306938633,"_s":"148ed141faa9e6bda8f7b0db67695a05"}
{"Time":"8000","fob_ID":"3","hub_ID":"0","Name":"33.32","Checked-In":"1","_id":{"$wrap":"$oid","v":80}}
{"k":"0000000080","o":"0000000103","v":"001"}
{"_id":81,"_uid":81,"_dt":1574306938640,"_s":"80701b583afee1d1d62d7e6a4a78821e"}
{"Time":"8000","fob_ID":"4","hub_ID":"1","Name":"39.43","Checked-In":"0","_id":{"$wrap":"$oid","v":81}}
